gophient/__init__.py
gophient/const.py
gophient/exc.py
gophient/types.py
gophient-2.0.0.dist-info/LICENSE
gophient-2.0.0.dist-info/METADATA
gophient-2.0.0.dist-info/WHEEL
gophient-2.0.0.dist-info/RECORD
