Metadata-Version: 2.1
Name: gophient
Version: 2.0.0
Summary: Client library for the Gopherspace
Home-page: https://github.com/arichr/gophient
License: MIT
Keywords: gopher,gophient,client,python3,gopher-client,gopherspace,module,library
Author: Arisu Wonderland
Author-email: arisuchr@riseup.net
Requires-Python: >=3.8,<4.0
Classifier: Development Status :: 5 - Production/Stable
Classifier: Intended Audience :: Developers
Classifier: License :: OSI Approved
Classifier: License :: OSI Approved :: MIT License
Classifier: Natural Language :: English
Classifier: Operating System :: OS Independent
Classifier: Programming Language :: Python
Classifier: Programming Language :: Python :: 3
Classifier: Programming Language :: Python :: 3.8
Classifier: Programming Language :: Python :: 3.9
Classifier: Programming Language :: Python :: 3.10
Classifier: Programming Language :: Python :: 3.11
Classifier: Programming Language :: Python :: 3.12
Classifier: Programming Language :: Python :: 3 :: Only
Classifier: Programming Language :: Python :: 3.13
Classifier: Topic :: Communications
Classifier: Topic :: Internet
Classifier: Topic :: Software Development :: Libraries
Classifier: Topic :: Software Development :: Libraries :: Python Modules
Project-URL: Documentation, https://arichr.github.io/gophient/
Project-URL: Repository, https://github.com/arichr/gophient
